{"center": {"lat": 39.5, "lon": -98.35}, "quarters": ["2024-05", "2024-06", "2024-07", "2024-08", "2024-09"], "data": {"2024-05": [{"city": "Arlington, VA", "lat": 38.8816, "lon": -77.091, "postings": 87, "remote_share": 0.184}, {"city": "Atlanta, GA", "lat": 33.749, "lon": -84.388, "postings": 400, "remote_share": 0.21}, {"city": "Austin, TX", "lat": 30.2672, "lon": -97.7431, "postings": 280, "remote_share": 0.154}, {"city": "Baltimore, MD", "lat": 39.2904, "lon": -76.6122, "postings": 70, "remote_share": 0.229}, {"city": "Boise, ID", "lat": 43.615, "lon": -116.2023, "postings": 77, "remote_share": 0.247}, {"city": "Boston, MA", "lat": 42.3601, "lon": -71.0589, "postings": 135, "remote_share": 0.148}, {"city": "Charlotte, NC", "lat": 35.2271, "lon": -80.8431, "postings": 237, "remote_share": 0.118}, {"city": "Chicago, IL", "lat": 41.8781, "lon": -87.6298, "postings": 348, "remote_share": 0.138}, {"city": "Cincinnati, OH", "lat": 39.1031, "lon": -84.512, "postings": 102, "remote_share": 0.127}, {"city": "Cleveland, OH", "lat": 41.4993, "lon": -81.6944, "postings": 109, "remote_share": 0.156}, {"city": "Columbia, SC", "lat": 34.0007, "lon": -81.0348, "postings": 32, "remote_share": 0.219}, {"city": "Columbus, OH", "lat": 39.9612, "lon": -82.9988, "postings": 113, "remote_share": 0.133}, {"city": "Dallas, TX", "lat": 32.7767, "lon": -96.797, "postings": 255, "remote_share": 0.184}, {"city": "Denver, CO", "lat": 39.7392, "lon": -104.9903, "postings": 109, "remote_share": 0.358}, {"city": "Des Moines, IA", "lat": 41.5868, "lon": -93.625, "postings": 59, "remote_share": 0.102}, {"city": "Detroit, MI", "lat": 42.3314, "lon": -83.0458, "postings": 115, "remote_share": 0.104}, {"city": "Hartford, CT", "lat": 41.7658, "lon": -72.6734, "postings": 71, "remote_share": 0.296}, {"city": "Houston, TX", "lat": 29.7604, "lon": -95.3698, "postings": 318, "remote_share": 0.138}, {"city": "Indianapolis, IN", "lat": 39.7684, "lon": -86.1581, "postings": 84, "remote_share": 0.226}, {"city": "Irvine, CA", "lat": 33.6846, "lon": -117.8265, "postings": 47, "remote_share": 0.17}, {"city": "Irving, TX", "lat": 32.814, "lon": -96.9489, "postings": 140, "remote_share": 0.143}, {"city": "Jackson, MS", "lat": 32.2988, "lon": -90.1848, "postings": 32, "remote_share": 0.156}, {"city": "Jacksonville, FL", "lat": 30.3322, "lon": -81.6557, "postings": 97, "remote_share": 0.113}, {"city": "Jersey City, NJ", "lat": 40.7178, "lon": -74.0431, "postings": 76, "remote_share": 0.184}, {"city": "Kansas City, MO", "lat": 39.0997, "lon": -94.5786, "postings": 77, "remote_share": 0.13}, {"city": "Las Vegas, NV", "lat": 36.1699, "lon": -115.1398, "postings": 66, "remote_share": 0.424}, {"city": "Little Rock, AR", "lat": 34.7465, "lon": -92.2896, "postings": 51, "remote_share": 0.255}, {"city": "Los Angeles, CA", "lat": 34.0522, "lon": -118.2437, "postings": 137, "remote_share": 0.19}, {"city": "Madison, WI", "lat": 43.0731, "lon": -89.4012, "postings": 34, "remote_share": 0.294}, {"city": "McLean, VA", "lat": 38.9339, "lon": -77.1773, "postings": 42, "remote_share": 0.214}, {"city": "Miami, FL", "lat": 25.7617, "lon": -80.1918, "postings": 125, "remote_share": 0.168}, {"city": "Milwaukee, WI", "lat": 43.0389, "lon": -87.9065, "postings": 76, "remote_share": 0.211}, {"city": "Minneapolis, MN", "lat": 44.9778, "lon": -93.265, "postings": 123, "remote_share": 0.228}, {"city": "Nashville, TN", "lat": 36.1627, "lon": -86.7816, "postings": 92, "remote_share": 0.272}, {"city": "New York, NY", "lat": 40.7128, "lon": -74.006, "postings": 445, "remote_share": 0.157}, {"city": "Oklahoma City, OK", "lat": 35.4676, "lon": -97.5164, "postings": 57, "remote_share": 0.211}, {"city": "Orlando, FL", "lat": 28.5383, "lon": -81.3792, "postings": 60, "remote_share": 0.15}, {"city": "Philadelphia, PA", "lat": 39.9526, "lon": -75.1652, "postings": 111, "remote_share": 0.135}, {"city": "Phoenix, AZ", "lat": 33.4484, "lon": -112.074, "postings": 126, "remote_share": 0.198}, {"city": "Pittsburgh, PA", "lat": 40.4406, "lon": -79.9959, "postings": 99, "remote_share": 0.162}, {"city": "Plano, TX", "lat": 33.0198, "lon": -96.6989, "postings": 108, "remote_share": 0.148}, {"city": "Portland, OR", "lat": 45.5152, "lon": -122.6784, "postings": 76, "remote_share": 0.368}, {"city": "Providence, RI", "lat": 41.824, "lon": -71.4128, "postings": 54, "remote_share": 0.352}, {"city": "Raleigh, NC", "lat": 35.7796, "lon": -78.6382, "postings": 103, "remote_share": 0.184}, {"city": "Richmond, VA", "lat": 37.5407, "lon": -77.436, "postings": 168, "remote_share": 0.196}, {"city": "Sacramento, CA", "lat": 38.5816, "lon": -121.4944, "postings": 50, "remote_share": 0.16}, {"city": "Saint Louis, MO", "lat": 38.627, "lon": -90.1994, "postings": 121, "remote_share": 0.223}, {"city": "Salt Lake City, UT", "lat": 40.7608, "lon": -111.891, "postings": 58, "remote_share": 0.172}, {"city": "San Antonio, TX", "lat": 29.4241, "lon": -98.4936, "postings": 102, "remote_share": 0.127}, {"city": "San Diego, CA", "lat": 32.7157, "lon": -117.1611, "postings": 100, "remote_share": 0.22}, {"city": "San Francisco, CA", "lat": 37.7749, "lon": -122.4194, "postings": 183, "remote_share": 0.202}, {"city": "San Jose, CA", "lat": 37.3382, "lon": -121.8863, "postings": 135, "remote_share": 0.133}, {"city": "Santa Clara, CA", "lat": 37.3541, "lon": -121.9552, "postings": 52, "remote_share": 0.154}, {"city": "Seattle, WA", "lat": 47.6062, "lon": -122.3321, "postings": 151, "remote_share": 0.238}, {"city": "Springfield, IL", "lat": 39.7817, "lon": -89.6501, "postings": 40, "remote_share": 0.3}, {"city": "Tallahassee, FL", "lat": 30.4383, "lon": -84.2807, "postings": 38, "remote_share": 0.237}, {"city": "Tampa, FL", "lat": 27.9506, "lon": -82.4572, "postings": 125, "remote_share": 0.096}, {"city": "Washington, DC", "lat": 38.9072, "lon": -77.0369, "postings": 203, "remote_share": 0.266}], "2024-06": [{"city": "Arlington, VA", "lat": 38.8816, "lon": -77.091, "postings": 65, "remote_share": 0.108}, {"city": "Atlanta, GA", "lat": 33.749, "lon": -84.388, "postings": 316, "remote_share": 0.161}, {"city": "Austin, TX", "lat": 30.2672, "lon": -97.7431, "postings": 258, "remote_share": 0.221}, {"city": "Baltimore, MD", "lat": 39.2904, "lon": -76.6122, "postings": 67, "remote_share": 0.313}, {"city": "Boise, ID", "lat": 43.615, "lon": -116.2023, "postings": 69, "remote_share": 0.304}, {"city": "Boston, MA", "lat": 42.3601, "lon": -71.0589, "postings": 169, "remote_share": 0.231}, {"city": "Charlotte, NC", "lat": 35.2271, "lon": -80.8431, "postings": 233, "remote_share": 0.116}, {"city": "Chicago, IL", "lat": 41.8781, "lon": -87.6298, "postings": 338, "remote_share": 0.145}, {"city": "Cincinnati, OH", "lat": 39.1031, "lon": -84.512, "postings": 106, "remote_share": 0.123}, {"city": "Cleveland, OH", "lat": 41.4993, "lon": -81.6944, "postings": 65, "remote_share": 0.123}, {"city": "Columbia, SC", "lat": 34.0007, "lon": -81.0348, "postings": 40, "remote_share": 0.35}, {"city": "Columbus, OH", "lat": 39.9612, "lon": -82.9988, "postings": 133, "remote_share": 0.203}, {"city": "Dallas, TX", "lat": 32.7767, "lon": -96.797, "postings": 257, "remote_share": 0.171}, {"city": "Denver, CO", "lat": 39.7392, "lon": -104.9903, "postings": 114, "remote_share": 0.219}, {"city": "Des Moines, IA", "lat": 41.5868, "lon": -93.625, "postings": 56, "remote_share": 0.232}, {"city": "Detroit, MI", "lat": 42.3314, "lon": -83.0458, "postings": 75, "remote_share": 0.147}, {"city": "Hartford, CT", "lat": 41.7658, "lon": -72.6734, "postings": 88, "remote_share": 0.216}, {"city": "Houston, TX", "lat": 29.7604, "lon": -95.3698, "postings": 297, "remote_share": 0.125}, {"city": "Indianapolis, IN", "lat": 39.7684, "lon": -86.1581, "postings": 104, "remote_share": 0.269}, {"city": "Irvine, CA", "lat": 33.6846, "lon": -117.8265, "postings": 48, "remote_share": 0.062}, {"city": "Irving, TX", "lat": 32.814, "lon": -96.9489, "postings": 90, "remote_share": 0.167}, {"city": "Jackson, MS", "lat": 32.2988, "lon": -90.1848, "postings": 90, "remote_share": 0.2}, {"city": "Jacksonville, FL", "lat": 30.3322, "lon": -81.6557, "postings": 57, "remote_share": 0.211}, {"city": "Jersey City, NJ", "lat": 40.7178, "lon": -74.0431, "postings": 64, "remote_share": 0.172}, {"city": "Kansas City, MO", "lat": 39.0997, "lon": -94.5786, "postings": 67, "remote_share": 0.119}, {"city": "Las Vegas, NV", "lat": 36.1699, "lon": -115.1398, "postings": 47, "remote_share": 0.191}, {"city": "Little Rock, AR", "lat": 34.7465, "lon": -92.2896, "postings": 39, "remote_share": 0.359}, {"city": "Los Angeles, CA", "lat": 34.0522, "lon": -118.2437, "postings": 163, "remote_share": 0.147}, {"city": "Madison, WI", "lat": 43.0731, "lon": -89.4012, "postings": 47, "remote_share": 0.319}, {"city": "McLean, VA", "lat": 38.9339, "lon": -77.1773, "postings": 83, "remote_share": 0.181}, {"city": "Miami, FL", "lat": 25.7617, "lon": -80.1918, "postings": 82, "remote_share": 0.146}, {"city": "Milwaukee, WI", "lat": 43.0389, "lon": -87.9065, "postings": 71, "remote_share": 0.169}, {"city": "Minneapolis, MN", "lat": 44.9778, "lon": -93.265, "postings": 116, "remote_share": 0.241}, {"city": "Nashville, TN", "lat": 36.1627, "lon": -86.7816, "postings": 108, "remote_share": 0.176}, {"city": "New York, NY", "lat": 40.7128, "lon": -74.006, "postings": 423, "remote_share": 0.139}, {"city": "Oklahoma City, OK", "lat": 35.4676, "lon": -97.5164, "postings": 83, "remote_share": 0.253}, {"city": "Orlando, FL", "lat": 28.5383, "lon": -81.3792, "postings": 48, "remote_share": 0.188}, {"city": "Philadelphia, PA", "lat": 39.9526, "lon": -75.1652, "postings": 110, "remote_share": 0.173}, {"city": "Phoenix, AZ", "lat": 33.4484, "lon": -112.074, "postings": 165, "remote_share": 0.218}, {"city": "Pittsburgh, PA", "lat": 40.4406, "lon": -79.9959, "postings": 78, "remote_share": 0.179}, {"city": "Plano, TX", "lat": 33.0198, "lon": -96.6989, "postings": 84, "remote_share": 0.202}, {"city": "Portland, OR", "lat": 45.5152, "lon": -122.6784, "postings": 48, "remote_share": 0.146}, {"city": "Providence, RI", "lat": 41.824, "lon": -71.4128, "postings": 49, "remote_share": 0.245}, {"city": "Raleigh, NC", "lat": 35.7796, "lon": -78.6382, "postings": 123, "remote_share": 0.211}, {"city": "Richmond, VA", "lat": 37.5407, "lon": -77.436, "postings": 168, "remote_share": 0.179}, {"city": "Sacramento, CA", "lat": 38.5816, "lon": -121.4944, "postings": 73, "remote_share": 0.247}, {"city": "Saint Louis, MO", "lat": 38.627, "lon": -90.1994, "postings": 66, "remote_share": 0.212}, {"city": "Salt Lake City, UT", "lat": 40.7608, "lon": -111.891, "postings": 82, "remote_share": 0.268}, {"city": "San Antonio, TX", "lat": 29.4241, "lon": -98.4936, "postings": 99, "remote_share": 0.051}, {"city": "San Diego, CA", "lat": 32.7157, "lon": -117.1611, "postings": 90, "remote_share": 0.167}, {"city": "San Francisco, CA", "lat": 37.7749, "lon": -122.4194, "postings": 208, "remote_share": 0.168}, {"city": "San Jose, CA", "lat": 37.3382, "lon": -121.8863, "postings": 82, "remote_share": 0.146}, {"city": "Santa Clara, CA", "lat": 37.3541, "lon": -121.9552, "postings": 25, "remote_share": 0.08}, {"city": "Seattle, WA", "lat": 47.6062, "lon": -122.3321, "postings": 139, "remote_share": 0.101}, {"city": "Springfield, IL", "lat": 39.7817, "lon": -89.6501, "postings": 60, "remote_share": 0.233}, {"city": "Tallahassee, FL", "lat": 30.4383, "lon": -84.2807, "postings": 104, "remote_share": 0.202}, {"city": "Tampa, FL", "lat": 27.9506, "lon": -82.4572, "postings": 127, "remote_share": 0.157}, {"city": "Washington, DC", "lat": 38.9072, "lon": -77.0369, "postings": 231, "remote_share": 0.26}], "2024-07": [{"city": "Arlington, VA", "lat": 38.8816, "lon": -77.091, "postings": 71, "remote_share": 0.239}, {"city": "Atlanta, GA", "lat": 33.749, "lon": -84.388, "postings": 269, "remote_share": 0.204}, {"city": "Austin, TX", "lat": 30.2672, "lon": -97.7431, "postings": 302, "remote_share": 0.126}, {"city": "Baltimore, MD", "lat": 39.2904, "lon": -76.6122, "postings": 58, "remote_share": 0.276}, {"city": "Boise, ID", "lat": 43.615, "lon": -116.2023, "postings": 68, "remote_share": 0.324}, {"city": "Boston, MA", "lat": 42.3601, "lon": -71.0589, "postings": 166, "remote_share": 0.223}, {"city": "Charlotte, NC", "lat": 35.2271, "lon": -80.8431, "postings": 232, "remote_share": 0.164}, {"city": "Chicago, IL", "lat": 41.8781, "lon": -87.6298, "postings": 345, "remote_share": 0.229}, {"city": "Cincinnati, OH", "lat": 39.1031, "lon": -84.512, "postings": 76, "remote_share": 0.184}, {"city": "Cleveland, OH", "lat": 41.4993, "lon": -81.6944, "postings": 66, "remote_share": 0.182}, {"city": "Columbia, SC", "lat": 34.0007, "lon": -81.0348, "postings": 52, "remote_share": 0.173}, {"city": "Columbus, OH", "lat": 39.9612, "lon": -82.9988, "postings": 119, "remote_share": 0.269}, {"city": "Dallas, TX", "lat": 32.7767, "lon": -96.797, "postings": 249, "remote_share": 0.149}, {"city": "Denver, CO", "lat": 39.7392, "lon": -104.9903, "postings": 103, "remote_share": 0.204}, {"city": "Des Moines, IA", "lat": 41.5868, "lon": -93.625, "postings": 54, "remote_share": 0.426}, {"city": "Detroit, MI", "lat": 42.3314, "lon": -83.0458, "postings": 43, "remote_share": 0.07}, {"city": "Hartford, CT", "lat": 41.7658, "lon": -72.6734, "postings": 54, "remote_share": 0.296}, {"city": "Houston, TX", "lat": 29.7604, "lon": -95.3698, "postings": 240, "remote_share": 0.138}, {"city": "Indianapolis, IN", "lat": 39.7684, "lon": -86.1581, "postings": 91, "remote_share": 0.275}, {"city": "Irvine, CA", "lat": 33.6846, "lon": -117.8265, "postings": 31, "remote_share": 0.226}, {"city": "Irving, TX", "lat": 32.814, "lon": -96.9489, "postings": 83, "remote_share": 0.12}, {"city": "Jackson, MS", "lat": 32.2988, "lon": -90.1848, "postings": 64, "remote_share": 0.219}, {"city": "Jacksonville, FL", "lat": 30.3322, "lon": -81.6557, "postings": 59, "remote_share": 0.237}, {"city": "Jersey City, NJ", "lat": 40.7178, "lon": -74.0431, "postings": 77, "remote_share": 0.13}, {"city": "Kansas City, MO", "lat": 39.0997, "lon": -94.5786, "postings": 46, "remote_share": 0.217}, {"city": "Las Vegas, NV", "lat": 36.1699, "lon": -115.1398, "postings": 54, "remote_share": 0.278}, {"city": "Little Rock, AR", "lat": 34.7465, "lon": -92.2896, "postings": 48, "remote_share": 0.271}, {"city": "Los Angeles, CA", "lat": 34.0522, "lon": -118.2437, "postings": 135, "remote_share": 0.244}, {"city": "Madison, WI", "lat": 43.0731, "lon": -89.4012, "postings": 51, "remote_share": 0.353}, {"city": "McLean, VA", "lat": 38.9339, "lon": -77.1773, "postings": 41, "remote_share": 0.293}, {"city": "Miami, FL", "lat": 25.7617, "lon": -80.1918, "postings": 77, "remote_share": 0.182}, {"city": "Milwaukee, WI", "lat": 43.0389, "lon": -87.9065, "postings": 66, "remote_share": 0.076}, {"city": "Minneapolis, MN", "lat": 44.9778, "lon": -93.265, "postings": 112, "remote_share": 0.268}, {"city": "Nashville, TN", "lat": 36.1627, "lon": -86.7816, "postings": 106, "remote_share": 0.226}, {"city": "New York, NY", "lat": 40.7128, "lon": -74.006, "postings": 357, "remote_share": 0.165}, {"city": "Oklahoma City, OK", "lat": 35.4676, "lon": -97.5164, "postings": 44, "remote_share": 0.25}, {"city": "Orlando, FL", "lat": 28.5383, "lon": -81.3792, "postings": 44, "remote_share": 0.205}, {"city": "Philadelphia, PA", "lat": 39.9526, "lon": -75.1652, "postings": 99, "remote_share": 0.141}, {"city": "Phoenix, AZ", "lat": 33.4484, "lon": -112.074, "postings": 113, "remote_share": 0.283}, {"city": "Pittsburgh, PA", "lat": 40.4406, "lon": -79.9959, "postings": 74, "remote_share": 0.162}, {"city": "Plano, TX", "lat": 33.0198, "lon": -96.6989, "postings": 100, "remote_share": 0.14}, {"city": "Portland, OR", "lat": 45.5152, "lon": -122.6784, "postings": 56, "remote_share": 0.375}, {"city": "Providence, RI", "lat": 41.824, "lon": -71.4128, "postings": 45, "remote_share": 0.356}, {"city": "Raleigh, NC", "lat": 35.7796, "lon": -78.6382, "postings": 98, "remote_share": 0.337}, {"city": "Richmond, VA", "lat": 37.5407, "lon": -77.436, "postings": 266, "remote_share": 0.147}, {"city": "Sacramento, CA", "lat": 38.5816, "lon": -121.4944, "postings": 48, "remote_share": 0.208}, {"city": "Saint Louis, MO", "lat": 38.627, "lon": -90.1994, "postings": 73, "remote_share": 0.192}, {"city": "Salt Lake City, UT", "lat": 40.7608, "lon": -111.891, "postings": 59, "remote_share": 0.254}, {"city": "San Antonio, TX", "lat": 29.4241, "lon": -98.4936, "postings": 105, "remote_share": 0.067}, {"city": "San Diego, CA", "lat": 32.7157, "lon": -117.1611, "postings": 80, "remote_share": 0.15}, {"city": "San Francisco, CA", "lat": 37.7749, "lon": -122.4194, "postings": 144, "remote_share": 0.264}, {"city": "San Jose, CA", "lat": 37.3382, "lon": -121.8863, "postings": 77, "remote_share": 0.13}, {"city": "Santa Clara, CA", "lat": 37.3541, "lon": -121.9552, "postings": 87, "remote_share": 0.046}, {"city": "Seattle, WA", "lat": 47.6062, "lon": -122.3321, "postings": 101, "remote_share": 0.228}, {"city": "Springfield, IL", "lat": 39.7817, "lon": -89.6501, "postings": 59, "remote_share": 0.373}, {"city": "Tallahassee, FL", "lat": 30.4383, "lon": -84.2807, "postings": 114, "remote_share": 0.167}, {"city": "Tampa, FL", "lat": 27.9506, "lon": -82.4572, "postings": 99, "remote_share": 0.162}, {"city": "Washington, DC", "lat": 38.9072, "lon": -77.0369, "postings": 201, "remote_share": 0.303}], "2024-08": [{"city": "Arlington, VA", "lat": 38.8816, "lon": -77.091, "postings": 96, "remote_share": 0.177}, {"city": "Atlanta, GA", "lat": 33.749, "lon": -84.388, "postings": 342, "remote_share": 0.246}, {"city": "Austin, TX", "lat": 30.2672, "lon": -97.7431, "postings": 292, "remote_share": 0.205}, {"city": "Baltimore, MD", "lat": 39.2904, "lon": -76.6122, "postings": 67, "remote_share": 0.194}, {"city": "Boise, ID", "lat": 43.615, "lon": -116.2023, "postings": 79, "remote_share": 0.443}, {"city": "Boston, MA", "lat": 42.3601, "lon": -71.0589, "postings": 249, "remote_share": 0.277}, {"city": "Charlotte, NC", "lat": 35.2271, "lon": -80.8431, "postings": 273, "remote_share": 0.154}, {"city": "Chicago, IL", "lat": 41.8781, "lon": -87.6298, "postings": 387, "remote_share": 0.189}, {"city": "Cincinnati, OH", "lat": 39.1031, "lon": -84.512, "postings": 87, "remote_share": 0.138}, {"city": "Cleveland, OH", "lat": 41.4993, "lon": -81.6944, "postings": 81, "remote_share": 0.173}, {"city": "Columbia, SC", "lat": 34.0007, "lon": -81.0348, "postings": 74, "remote_share": 0.365}, {"city": "Columbus, OH", "lat": 39.9612, "lon": -82.9988, "postings": 134, "remote_share": 0.284}, {"city": "Dallas, TX", "lat": 32.7767, "lon": -96.797, "postings": 271, "remote_share": 0.155}, {"city": "Denver, CO", "lat": 39.7392, "lon": -104.9903, "postings": 157, "remote_share": 0.395}, {"city": "Des Moines, IA", "lat": 41.5868, "lon": -93.625, "postings": 75, "remote_share": 0.36}, {"city": "Detroit, MI", "lat": 42.3314, "lon": -83.0458, "postings": 69, "remote_share": 0.203}, {"city": "Hartford, CT", "lat": 41.7658, "lon": -72.6734, "postings": 65, "remote_share": 0.308}, {"city": "Houston, TX", "lat": 29.7604, "lon": -95.3698, "postings": 264, "remote_share": 0.17}, {"city": "Indianapolis, IN", "lat": 39.7684, "lon": -86.1581, "postings": 144, "remote_share": 0.312}, {"city": "Irvine, CA", "lat": 33.6846, "lon": -117.8265, "postings": 55, "remote_share": 0.091}, {"city": "Irving, TX", "lat": 32.814, "lon": -96.9489, "postings": 114, "remote_share": 0.149}, {"city": "Jackson, MS", "lat": 32.2988, "lon": -90.1848, "postings": 56, "remote_share": 0.464}, {"city": "Jacksonville, FL", "lat": 30.3322, "lon": -81.6557, "postings": 85, "remote_share": 0.141}, {"city": "Jersey City, NJ", "lat": 40.7178, "lon": -74.0431, "postings": 81, "remote_share": 0.185}, {"city": "Kansas City, MO", "lat": 39.0997, "lon": -94.5786, "postings": 45, "remote_share": 0.044}, {"city": "Las Vegas, NV", "lat": 36.1699, "lon": -115.1398, "postings": 58, "remote_share": 0.138}, {"city": "Little Rock, AR", "lat": 34.7465, "lon": -92.2896, "postings": 71, "remote_share": 0.296}, {"city": "Los Angeles, CA", "lat": 34.0522, "lon": -118.2437, "postings": 148, "remote_share": 0.216}, {"city": "Madison, WI", "lat": 43.0731, "lon": -89.4012, "postings": 67, "remote_share": 0.403}, {"city": "McLean, VA", "lat": 38.9339, "lon": -77.1773, "postings": 67, "remote_share": 0.134}, {"city": "Miami, FL", "lat": 25.7617, "lon": -80.1918, "postings": 89, "remote_share": 0.281}, {"city": "Milwaukee, WI", "lat": 43.0389, "lon": -87.9065, "postings": 66, "remote_share": 0.182}, {"city": "Minneapolis, MN", "lat": 44.9778, "lon": -93.265, "postings": 106, "remote_share": 0.189}, {"city": "Nashville, TN", "lat": 36.1627, "lon": -86.7816, "postings": 130, "remote_share": 0.315}, {"city": "New York, NY", "lat": 40.7128, "lon": -74.006, "postings": 481, "remote_share": 0.191}, {"city": "Oklahoma City, OK", "lat": 35.4676, "lon": -97.5164, "postings": 83, "remote_share": 0.289}, {"city": "Orlando, FL", "lat": 28.5383, "lon": -81.3792, "postings": 38, "remote_share": 0.132}, {"city": "Philadelphia, PA", "lat": 39.9526, "lon": -75.1652, "postings": 122, "remote_share": 0.197}, {"city": "Phoenix, AZ", "lat": 33.4484, "lon": -112.074, "postings": 196, "remote_share": 0.306}, {"city": "Pittsburgh, PA", "lat": 40.4406, "lon": -79.9959, "postings": 54, "remote_share": 0.13}, {"city": "Plano, TX", "lat": 33.0198, "lon": -96.6989, "postings": 114, "remote_share": 0.158}, {"city": "Portland, OR", "lat": 45.5152, "lon": -122.6784, "postings": 71, "remote_share": 0.197}, {"city": "Providence, RI", "lat": 41.824, "lon": -71.4128, "postings": 64, "remote_share": 0.469}, {"city": "Raleigh, NC", "lat": 35.7796, "lon": -78.6382, "postings": 110, "remote_share": 0.291}, {"city": "Richmond, VA", "lat": 37.5407, "lon": -77.436, "postings": 142, "remote_share": 0.268}, {"city": "Sacramento, CA", "lat": 38.5816, "lon": -121.4944, "postings": 79, "remote_share": 0.418}, {"city": "Saint Louis, MO", "lat": 38.627, "lon": -90.1994, "postings": 89, "remote_share": 0.191}, {"city": "Salt Lake City, UT", "lat": 40.7608, "lon": -111.891, "postings": 94, "remote_share": 0.394}, {"city": "San Antonio, TX", "lat": 29.4241, "lon": -98.4936, "postings": 97, "remote_share": 0.113}, {"city": "San Diego, CA", "lat": 32.7157, "lon": -117.1611, "postings": 77, "remote_share": 0.117}, {"city": "San Francisco, CA", "lat": 37.7749, "lon": -122.4194, "postings": 159, "remote_share": 0.233}, {"city": "San Jose, CA", "lat": 37.3382, "lon": -121.8863, "postings": 103, "remote_share": 0.146}, {"city": "Santa Clara, CA", "lat": 37.3541, "lon": -121.9552, "postings": 66, "remote_share": 0.121}, {"city": "Seattle, WA", "lat": 47.6062, "lon": -122.3321, "postings": 134, "remote_share": 0.149}, {"city": "Springfield, IL", "lat": 39.7817, "lon": -89.6501, "postings": 75, "remote_share": 0.4}, {"city": "Tallahassee, FL", "lat": 30.4383, "lon": -84.2807, "postings": 101, "remote_share": 0.277}, {"city": "Tampa, FL", "lat": 27.9506, "lon": -82.4572, "postings": 119, "remote_share": 0.202}, {"city": "Washington, DC", "lat": 38.9072, "lon": -77.0369, "postings": 297, "remote_share": 0.293}], "2024-09": [{"city": "Arlington, VA", "lat": 38.8816, "lon": -77.091, "postings": 85, "remote_share": 0.118}, {"city": "Atlanta, GA", "lat": 33.749, "lon": -84.388, "postings": 379, "remote_share": 0.201}, {"city": "Austin, TX", "lat": 30.2672, "lon": -97.7431, "postings": 331, "remote_share": 0.151}, {"city": "Baltimore, MD", "lat": 39.2904, "lon": -76.6122, "postings": 49, "remote_share": 0.367}, {"city": "Boise, ID", "lat": 43.615, "lon": -116.2023, "postings": 50, "remote_share": 0.32}, {"city": "Boston, MA", "lat": 42.3601, "lon": -71.0589, "postings": 293, "remote_share": 0.181}, {"city": "Charlotte, NC", "lat": 35.2271, "lon": -80.8431, "postings": 251, "remote_share": 0.159}, {"city": "Chicago, IL", "lat": 41.8781, "lon": -87.6298, "postings": 385, "remote_share": 0.164}, {"city": "Cincinnati, OH", "lat": 39.1031, "lon": -84.512, "postings": 92, "remote_share": 0.141}, {"city": "Cleveland, OH", "lat": 41.4993, "lon": -81.6944, "postings": 103, "remote_share": 0.107}, {"city": "Columbia, SC", "lat": 34.0007, "lon": -81.0348, "postings": 53, "remote_share": 0.283}, {"city": "Columbus, OH", "lat": 39.9612, "lon": -82.9988, "postings": 148, "remote_share": 0.223}, {"city": "Dallas, TX", "lat": 32.7767, "lon": -96.797, "postings": 294, "remote_share": 0.173}, {"city": "Denver, CO", "lat": 39.7392, "lon": -104.9903, "postings": 147, "remote_share": 0.231}, {"city": "Des Moines, IA", "lat": 41.5868, "lon": -93.625, "postings": 68, "remote_share": 0.206}, {"city": "Detroit, MI", "lat": 42.3314, "lon": -83.0458, "postings": 90, "remote_share": 0.078}, {"city": "Hartford, CT", "lat": 41.7658, "lon": -72.6734, "postings": 68, "remote_share": 0.265}, {"city": "Houston, TX", "lat": 29.7604, "lon": -95.3698, "postings": 304, "remote_share": 0.109}, {"city": "Indianapolis, IN", "lat": 39.7684, "lon": -86.1581, "postings": 111, "remote_share": 0.297}, {"city": "Irvine, CA", "lat": 33.6846, "lon": -117.8265, "postings": 63, "remote_share": 0.127}, {"city": "Irving, TX", "lat": 32.814, "lon": -96.9489, "postings": 128, "remote_share": 0.203}, {"city": "Jackson, MS", "lat": 32.2988, "lon": -90.1848, "postings": 71, "remote_share": 0.254}, {"city": "Jacksonville, FL", "lat": 30.3322, "lon": -81.6557, "postings": 57, "remote_share": 0.14}, {"city": "Jersey City, NJ", "lat": 40.7178, "lon": -74.0431, "postings": 56, "remote_share": 0.125}, {"city": "Kansas City, MO", "lat": 39.0997, "lon": -94.5786, "postings": 63, "remote_share": 0.095}, {"city": "Las Vegas, NV", "lat": 36.1699, "lon": -115.1398, "postings": 44, "remote_share": 0.182}, {"city": "Little Rock, AR", "lat": 34.7465, "lon": -92.2896, "postings": 50, "remote_share": 0.34}, {"city": "Los Angeles, CA", "lat": 34.0522, "lon": -118.2437, "postings": 154, "remote_share": 0.234}, {"city": "Madison, WI", "lat": 43.0731, "lon": -89.4012, "postings": 46, "remote_share": 0.435}, {"city": "McLean, VA", "lat": 38.9339, "lon": -77.1773, "postings": 70, "remote_share": 0.129}, {"city": "Miami, FL", "lat": 25.7617, "lon": -80.1918, "postings": 76, "remote_share": 0.105}, {"city": "Milwaukee, WI", "lat": 43.0389, "lon": -87.9065, "postings": 75, "remote_share": 0.08}, {"city": "Minneapolis, MN", "lat": 44.9778, "lon": -93.265, "postings": 149, "remote_share": 0.188}, {"city": "Nashville, TN", "lat": 36.1627, "lon": -86.7816, "postings": 124, "remote_share": 0.25}, {"city": "New York, NY", "lat": 40.7128, "lon": -74.006, "postings": 469, "remote_share": 0.162}, {"city": "Oklahoma City, OK", "lat": 35.4676, "lon": -97.5164, "postings": 83, "remote_share": 0.241}, {"city": "Orlando, FL", "lat": 28.5383, "lon": -81.3792, "postings": 51, "remote_share": 0.216}, {"city": "Philadelphia, PA", "lat": 39.9526, "lon": -75.1652, "postings": 153, "remote_share": 0.203}, {"city": "Phoenix, AZ", "lat": 33.4484, "lon": -112.074, "postings": 159, "remote_share": 0.195}, {"city": "Pittsburgh, PA", "lat": 40.4406, "lon": -79.9959, "postings": 89, "remote_share": 0.135}, {"city": "Plano, TX", "lat": 33.0198, "lon": -96.6989, "postings": 103, "remote_share": 0.175}, {"city": "Portland, OR", "lat": 45.5152, "lon": -122.6784, "postings": 96, "remote_share": 0.198}, {"city": "Providence, RI", "lat": 41.824, "lon": -71.4128, "postings": 42, "remote_share": 0.452}, {"city": "Raleigh, NC", "lat": 35.7796, "lon": -78.6382, "postings": 134, "remote_share": 0.261}, {"city": "Richmond, VA", "lat": 37.5407, "lon": -77.436, "postings": 140, "remote_share": 0.186}, {"city": "Sacramento, CA", "lat": 38.5816, "lon": -121.4944, "postings": 84, "remote_share": 0.333}, {"city": "Saint Louis, MO", "lat": 38.627, "lon": -90.1994, "postings": 89, "remote_share": 0.124}, {"city": "Salt Lake City, UT", "lat": 40.7608, "lon": -111.891, "postings": 63, "remote_share": 0.238}, {"city": "San Antonio, TX", "lat": 29.4241, "lon": -98.4936, "postings": 87, "remote_share": 0.161}, {"city": "San Diego, CA", "lat": 32.7157, "lon": -117.1611, "postings": 115, "remote_share": 0.165}, {"city": "San Francisco, CA", "lat": 37.7749, "lon": -122.4194, "postings": 182, "remote_share": 0.291}, {"city": "San Jose, CA", "lat": 37.3382, "lon": -121.8863, "postings": 118, "remote_share": 0.102}, {"city": "Santa Clara, CA", "lat": 37.3541, "lon": -121.9552, "postings": 32, "remote_share": 0.062}, {"city": "Seattle, WA", "lat": 47.6062, "lon": -122.3321, "postings": 125, "remote_share": 0.208}, {"city": "Springfield, IL", "lat": 39.7817, "lon": -89.6501, "postings": 57, "remote_share": 0.368}, {"city": "Tallahassee, FL", "lat": 30.4383, "lon": -84.2807, "postings": 92, "remote_share": 0.25}, {"city": "Tampa, FL", "lat": 27.9506, "lon": -82.4572, "postings": 147, "remote_share": 0.177}, {"city": "Washington, DC", "lat": 38.9072, "lon": -77.0369, "postings": 278, "remote_share": 0.209}]}}